ptw/__init__.py
ptw/__main__.py
ptw/asdnotify.py
ptw/connpool.py
ptw/constants.py
ptw/listener.py
ptw/proxy_protocol.py
ptw/utils.py
ptw-1.0.1.dist-info/LICENSE
ptw-1.0.1.dist-info/METADATA
ptw-1.0.1.dist-info/WHEEL
ptw-1.0.1.dist-info/entry_points.txt
ptw-1.0.1.dist-info/top_level.txt
ptw-1.0.1.dist-info/zip-safe
ptw-1.0.1.dist-info/RECORD
