Metadata-Version: 2.1
Name: ptw
Version: 1.0.1
Summary: Pooling TLS Wrapper
Home-page: https://github.com/Snawoot/ptw
Author: Vladislav Yarmak
Author-email: vladislav-ex-src@vm-0.com
License: MIT
Platform: UNKNOWN
Classifier: Programming Language :: Python :: 3.5
Classifier: License :: OSI Approved :: MIT License
Classifier: Operating System :: OS Independent
Classifier: Development Status :: 5 - Production/Stable
Classifier: Environment :: No Input/Output (Daemon)
Classifier: Intended Audience :: System Administrators
Classifier: Natural Language :: English
Classifier: Topic :: Internet
Classifier: Topic :: Security
Requires-Python: >=3.5.3
Provides-Extra: uvloop
Requires-Dist: uvloop (>=0.11.0) ; extra == 'uvloop'
